storjstatus/__init__.py
storjstatus/storjstatus_common.py
storjstatus/storjstatus_register.py
storjstatus/storjstatus_send.py
storjstatus/version.py
storjstatus-0.3.5.dist-info/DESCRIPTION.rst
storjstatus-0.3.5.dist-info/METADATA
storjstatus-0.3.5.dist-info/RECORD
storjstatus-0.3.5.dist-info/WHEEL
storjstatus-0.3.5.dist-info/entry_points.txt
storjstatus-0.3.5.dist-info/metadata.json
storjstatus-0.3.5.dist-info/top_level.txt
