Metadata-Version: 2.0
Name: storjstatus
Version: 0.3.5
Summary: A utility for reporting Storj farmer statistics
Home-page: https://www.storjstatus.com/
Author: James Coyle
Author-email: james.coyle@jamesdcoyle.net
License: MIT
Platform: UNKNOWN
Requires-Dist: jstyleson (==0.0.2)
Requires-Dist: python-crontab (==2.2.8)
Requires-Dist: requests (==2.18.4)
